webapp_health_check
