Metadata-Version: 1.1
Name: webapp-health-check
Version: 1.5
Summary: wen app health plugin
Home-page: https://github.com/matiasgrana/web_app_health_check
Author: Matias Graña
Author-email: maicolmatiasg@gmail.com
License: MIT
Platform: UNKNOWN
Classifier: Development Status :: 5 - Production/Stable
Classifier: Intended Audience :: System Administrators
Classifier: License :: OSI Approved :: MIT License
Classifier: Programming Language :: Python :: 3
Classifier: Programming Language :: Python :: 3 :: Only
Classifier: Topic :: System :: Monitoring
